{
    "base": "includes\\assets\\vendors\\semantic\\",
    "paths": {
        "source": {
            "config": "src/theme.config",
            "definitions": "src/definitions/",
            "site": "src/site/",
            "themes": "src/themes/"
        },
        "output": {
            "packaged": "bundle\\",
            "uncompressed": "bundle\\components\\",
            "compressed": "bundle\\components\\",
            "themes": "bundle\\themes\\"
        },
        "clean": "bundle/"
    },
    "permission": false,
    "autoInstall": false,
    "rtl": false,
    "components": [
        "button",
        "icon",
        "image",
        "input",
        "label",
        "segment",
        "form",
        "grid",
        "message",
        "table",
        "card",
        "accordion",
        "checkbox",
        "dimmer",
        "dropdown",
        "modal",
        "progress",
        "rating",
        "search",
        "transition",
        "api",
        "form"
    ],
    "version": "2.4.2"
}
